{"team":"KiPe06","slug":"kipe06","season":{"id":152,"year":2022,"series":"Miesten Suomensarja"},"roster":[{"player_id":9806,"name":"Arttu Lehto","games":18,"turns_at_bat":132,"pos":"3P","spark_index":116,"adv_plus":119,"runner_plus":114,"out_avoid_plus":114,"teho_plus":224},{"player_id":6446,"name":"Eetu Ojala","games":18,"turns_at_bat":128,"pos":"1V","spark_index":116,"adv_plus":122,"runner_plus":115,"out_avoid_plus":102,"teho_plus":204},{"player_id":11196,"name":"Leevi Immonen","games":17,"turns_at_bat":130,"pos":"3K","spark_index":114,"adv_plus":120,"runner_plus":109,"out_avoid_plus":106,"teho_plus":102},{"player_id":6871,"name":"Anttoni Jokinen","games":11,"turns_at_bat":89,"pos":"2P","spark_index":110,"adv_plus":115,"runner_plus":107,"out_avoid_plus":103,"teho_plus":109},{"player_id":7841,"name":"Joonas Maunu","games":16,"turns_at_bat":122,"pos":"3P","spark_index":109,"adv_plus":115,"runner_plus":107,"out_avoid_plus":97,"teho_plus":105},{"player_id":4413,"name":"Panu Pasanen","games":17,"turns_at_bat":126,"pos":"3P","spark_index":106,"adv_plus":109,"runner_plus":115,"out_avoid_plus":84,"teho_plus":133},{"player_id":11211,"name":"Leo Sivusalo","games":16,"turns_at_bat":115,"pos":null,"spark_index":102,"adv_plus":111,"runner_plus":104,"out_avoid_plus":75,"teho_plus":100},{"player_id":9390,"name":"Juuso Luostari","games":18,"turns_at_bat":125,"pos":"2V","spark_index":101,"adv_plus":95,"runner_plus":105,"out_avoid_plus":108,"teho_plus":159},{"player_id":9522,"name":"Henrik Ristolainen","games":17,"turns_at_bat":116,"pos":"3V","spark_index":100,"adv_plus":91,"runner_plus":98,"out_avoid_plus":124,"teho_plus":141},{"player_id":6712,"name":"Petri Kallela","games":14,"turns_at_bat":81,"pos":"S","spark_index":95,"adv_plus":89,"runner_plus":92,"out_avoid_plus":115,"teho_plus":109},{"player_id":5015,"name":"Jussi Alatalo","games":18,"turns_at_bat":116,"pos":"L","spark_index":93,"adv_plus":88,"runner_plus":87,"out_avoid_plus":114,"teho_plus":80},{"player_id":11278,"name":"Juho Saarvo","games":9,"turns_at_bat":44,"pos":"L","spark_index":91,"adv_plus":85,"runner_plus":86,"out_avoid_plus":112,"teho_plus":50},{"player_id":4070,"name":"Jukka Raittila","games":5,"turns_at_bat":23,"pos":null,"spark_index":90,"adv_plus":86,"runner_plus":76,"out_avoid_plus":123,"teho_plus":96},{"player_id":9804,"name":"Eeli Jaakkola","games":16,"turns_at_bat":101,"pos":"2K","spark_index":88,"adv_plus":83,"runner_plus":83,"out_avoid_plus":110,"teho_plus":61},{"player_id":12445,"name":"Samu Vesanen","games":2,"turns_at_bat":14,"pos":null,"spark_index":72,"adv_plus":69,"runner_plus":63,"out_avoid_plus":91,"teho_plus":32},{"player_id":6136,"name":"Tuukka Mansikkamäki","games":2,"turns_at_bat":12,"pos":"S","spark_index":67,"adv_plus":68,"runner_plus":54,"out_avoid_plus":82,"teho_plus":37},{"player_id":11210,"name":"Veeti Sainio","games":1,"turns_at_bat":3,"pos":"S","spark_index":61,"adv_plus":41,"runner_plus":40,"out_avoid_plus":141,"teho_plus":0},{"player_id":10399,"name":"Lauri Kosonen","games":1,"turns_at_bat":5,"pos":null,"spark_index":56,"adv_plus":37,"runner_plus":69,"out_avoid_plus":85,"teho_plus":88}],"standing":{"team":"KiPe06","games":18,"wins":12,"super_wins":4,"super_losses":1,"ties":0,"losses":6,"points":33,"runs_for":215,"runs_against":126,"run_diff":89}}