{"team":"Mansen Räpsä","slug":"mansen-rapsa","season":{"id":84,"year":2015,"series":"Naisten Superpesis"},"roster":[{"player_id":2545,"name":"Jatta Vuorinen","games":24,"turns_at_bat":166,"pos":"3P","spark_index":119,"adv_plus":128,"runner_plus":116,"out_avoid_plus":100,"teho_plus":113},{"player_id":27198,"name":"Susanna Kylä-Kause","games":24,"turns_at_bat":121,"pos":null,"spark_index":115,"adv_plus":108,"runner_plus":130,"out_avoid_plus":109,"teho_plus":233},{"player_id":5045,"name":"Kirsi Ala-Lipasti","games":23,"turns_at_bat":165,"pos":"3V","spark_index":111,"adv_plus":122,"runner_plus":114,"out_avoid_plus":78,"teho_plus":131},{"player_id":3237,"name":"Nina Taipale","games":24,"turns_at_bat":165,"pos":"2V","spark_index":105,"adv_plus":103,"runner_plus":104,"out_avoid_plus":110,"teho_plus":109},{"player_id":4482,"name":"Salla Kilpeläinen","games":14,"turns_at_bat":101,"pos":"3K","spark_index":103,"adv_plus":108,"runner_plus":108,"out_avoid_plus":85,"teho_plus":136},{"player_id":16931,"name":"Sanna Ahola","games":24,"turns_at_bat":154,"pos":"1V","spark_index":98,"adv_plus":99,"runner_plus":98,"out_avoid_plus":96,"teho_plus":75},{"player_id":4538,"name":"Camilla Kirsilä","games":13,"turns_at_bat":92,"pos":"3K","spark_index":98,"adv_plus":100,"runner_plus":97,"out_avoid_plus":92,"teho_plus":94},{"player_id":3432,"name":"Anne Tolonen","games":24,"turns_at_bat":165,"pos":"2P","spark_index":94,"adv_plus":99,"runner_plus":101,"out_avoid_plus":73,"teho_plus":96},{"player_id":6324,"name":"Leena Ojanen","games":24,"turns_at_bat":136,"pos":"L","spark_index":94,"adv_plus":92,"runner_plus":81,"out_avoid_plus":121,"teho_plus":21},{"player_id":6265,"name":"Heidi Vulli","games":23,"turns_at_bat":120,"pos":"3V","spark_index":93,"adv_plus":94,"runner_plus":93,"out_avoid_plus":92,"teho_plus":54},{"player_id":4896,"name":"Anna Rintanen","games":24,"turns_at_bat":144,"pos":"S","spark_index":88,"adv_plus":75,"runner_plus":80,"out_avoid_plus":133,"teho_plus":50},{"player_id":7464,"name":"Stina Parantainen","games":20,"turns_at_bat":107,"pos":"2K","spark_index":82,"adv_plus":79,"runner_plus":66,"out_avoid_plus":115,"teho_plus":54},{"player_id":2459,"name":"Petra Pihlström","games":22,"turns_at_bat":140,"pos":"3K","spark_index":80,"adv_plus":67,"runner_plus":88,"out_avoid_plus":103,"teho_plus":67},{"player_id":4897,"name":"Milja Vehmaanperä","games":5,"turns_at_bat":32,"pos":null,"spark_index":80,"adv_plus":76,"runner_plus":83,"out_avoid_plus":85,"teho_plus":90}],"standing":{"team":"Mansen Räpsä","games":24,"wins":11,"super_wins":3,"super_losses":2,"ties":0,"losses":13,"points":32,"runs_for":126,"runs_against":97,"run_diff":29}}