{"player":{"id":12903,"name":"Tiitu Uusitalo","born_year":null},"career":[{"player_id":12903,"name":"Tiitu Uusitalo","born_year":null,"year":2026,"games":15,"team":"KaMa","turns_at_bat":73,"kunnarit":2,"lyodyt":6,"tuodut":6,"karkilyonnit":47,"karki_yritykset":74,"saatot":110,"saatto_yritykset":164,"etenemiset":82,"eteneminen_yritykset":134,"haavat":31,"palot":21,"season_id":3,"tehot":14,"kl_pct":0.6351351351351351,"saatto_pct":0.6707317073170732,"eten_pct":0.6119402985074627,"kunnari_rate":0.0273972602739726,"lyoty_rate":0.0821917808219178,"tuotu_rate":0.04477611940298507,"haava_rate":0.4246575342465753,"palo_rate":0.2876712328767123,"tehot_per_turn":0.1917808219178082,"kl_per_turn":0.6438356164383562,"hr_rbi_per_turn":0.1095890410958904,"kl_base0":0.42857142857142855,"kl_base0_tries":7,"kl_base1":0.5185185185185185,"kl_base1_tries":27,"kl_base2":0.7333333333333333,"kl_base2_tries":30,"kl_base3":0.8,"kl_base3_tries":10,"adv1_pct":0.42857142857142855,"adv2_pct":0.5185185185185185,"adv3_pct":0.7333333333333333,"adv_home_pct":0.8,"money_kl_pct":0.8,"money_kl_tries":10,"teho_plus":114,"adv_plus":117,"runner_plus":104,"out_avoid_plus":106,"adv1_plus":90,"adv2_plus":94,"adv3_plus":128,"adv_home_plus":177,"money_kl_plus":177,"spark_index":111,"teho_plus_adj":108}],"line":{"player_id":12903,"name":"Tiitu Uusitalo","born_year":null,"year":2026,"games":15,"team":"KaMa","turns_at_bat":73,"kunnarit":2,"lyodyt":6,"tuodut":6,"karkilyonnit":47,"karki_yritykset":74,"saatot":110,"saatto_yritykset":164,"etenemiset":82,"eteneminen_yritykset":134,"haavat":31,"palot":21,"season_id":3,"tehot":14,"kl_pct":0.6351351351351351,"saatto_pct":0.6707317073170732,"eten_pct":0.6119402985074627,"kunnari_rate":0.0273972602739726,"lyoty_rate":0.0821917808219178,"tuotu_rate":0.04477611940298507,"haava_rate":0.4246575342465753,"palo_rate":0.2876712328767123,"tehot_per_turn":0.1917808219178082,"kl_per_turn":0.6438356164383562,"hr_rbi_per_turn":0.1095890410958904,"kl_base0":0.42857142857142855,"kl_base0_tries":7,"kl_base1":0.5185185185185185,"kl_base1_tries":27,"kl_base2":0.7333333333333333,"kl_base2_tries":30,"kl_base3":0.8,"kl_base3_tries":10,"adv1_pct":0.42857142857142855,"adv2_pct":0.5185185185185185,"adv3_pct":0.7333333333333333,"adv_home_pct":0.8,"money_kl_pct":0.8,"money_kl_tries":10,"teho_plus":114,"adv_plus":117,"runner_plus":104,"out_avoid_plus":106,"adv1_plus":90,"adv2_plus":94,"adv3_plus":128,"adv_home_plus":177,"money_kl_plus":177,"spark_index":111,"teho_plus_adj":108,"pct_kl_pct":94,"pct_saatto_pct":83,"pct_eten_pct":64,"pct_kunnari_rate":97,"pct_lyoty_rate":69,"pct_palo_rate":58,"pct_tehot_per_turn":69},"proj":{"player_id":12903,"name":"Tiitu Uusitalo","as_of":"2026-07-02","age":null,"stats":{"kl_pct":{"rate":0.5767455952279432,"effective_n":67.7653620088117,"observed":0.6327862684539605},"saatto_pct":{"rate":0.6540863045011694,"effective_n":145.6969807227107,"observed":0.6710936364509087},"eten_pct":{"rate":0.604994638842744,"effective_n":118.88522558873822,"observed":0.6111595260217236},"kunnari_rate":{"rate":0.013759131231320049,"effective_n":68.91358098111536,"observed":0.026627994165457147},"lyoty_rate":{"rate":0.07837230013274761,"effective_n":66.97693789059271,"observed":0.08093154679641107},"haava_rate":{"rate":0.420931197859777,"effective_n":63.30371036434886,"observed":0.41737493894821237},"palo_rate":{"rate":0.31183622617898565,"effective_n":65.10781871403056,"observed":0.2912009271665777}},"teho_plus_proj":162},"career_json":[{"year":2026,"kl_pct":0.6351351351351351,"teho_plus":114}],"pct_stats":["kl_pct","saatto_pct","eten_pct","kunnari_rate","lyoty_rate","palo_rate","tehot_per_turn"],"base_kl":{"player_id":12903,"turns_at_bat":73,"kl_base0":0.42857142857142855,"kl_base0_tries":7,"kl_base1":0.5185185185185185,"kl_base1_tries":27,"kl_base2":0.7333333333333333,"kl_base2_tries":30,"kl_base3":0.8,"kl_base3_tries":10,"pct_kl_base0":51,"pct_kl_base1":45,"pct_kl_base2":82,"pct_kl_base3":87},"base_keys":["kl_base0","kl_base1","kl_base2","kl_base3"],"log":[{"player_id":12903,"season_id":3,"match_id":129565,"date":"2026-05-06","team":"KaMa","opponent":"NJ","home":1,"turns_at_bat":2,"kunnarit":0,"lyodyt":0,"tuodut":0,"karkilyonnit":0,"karki_yritykset":2,"saatot":0,"saatto_yritykset":4,"etenemiset":0,"eteneminen_yritykset":2,"haavat":2,"palot":0,"stadium":"Kankaanpää Areena","tehot":0,"kl_pct":0.0},{"player_id":12903,"season_id":3,"match_id":129573,"date":"2026-05-14","team":"KaMa","opponent":"SMJ","home":0,"turns_at_bat":5,"kunnarit":0,"lyodyt":0,"tuodut":0,"karkilyonnit":2,"karki_yritykset":5,"saatot":3,"saatto_yritykset":9,"etenemiset":5,"eteneminen_yritykset":9,"haavat":2,"palot":2,"stadium":"Unico Areena, Seinäjoki","tehot":0,"kl_pct":0.4},{"player_id":12903,"season_id":3,"match_id":129579,"date":"2026-05-17","team":"KaMa","opponent":"Ura","home":1,"turns_at_bat":3,"kunnarit":0,"lyodyt":0,"tuodut":0,"karkilyonnit":0,"karki_yritykset":1,"saatot":1,"saatto_yritykset":2,"etenemiset":1,"eteneminen_yritykset":4,"haavat":2,"palot":1,"stadium":"Kankaanpää Areena","tehot":0,"kl_pct":0.0},{"player_id":12903,"season_id":3,"match_id":129583,"date":"2026-05-20","team":"KaMa","opponent":"NJ","home":0,"turns_at_bat":8,"kunnarit":2,"lyodyt":4,"tuodut":4,"karkilyonnit":14,"karki_yritykset":15,"saatot":25,"saatto_yritykset":31,"etenemiset":17,"eteneminen_yritykset":21,"haavat":4,"palot":0,"stadium":"Unico Areena, Seinäjoki","tehot":10,"kl_pct":0.9333333333333333},{"player_id":12903,"season_id":3,"match_id":129588,"date":"2026-05-23","team":"KaMa","opponent":"SMJ","home":1,"turns_at_bat":6,"kunnarit":0,"lyodyt":0,"tuodut":0,"karkilyonnit":4,"karki_yritykset":4,"saatot":13,"saatto_yritykset":15,"etenemiset":9,"eteneminen_yritykset":14,"haavat":4,"palot":1,"stadium":"Huikoo Areena, Pori","tehot":0,"kl_pct":1.0},{"player_id":12903,"season_id":3,"match_id":129595,"date":"2026-05-29","team":"KaMa","opponent":"PuMu","home":1,"turns_at_bat":7,"kunnarit":0,"lyodyt":0,"tuodut":2,"karkilyonnit":5,"karki_yritykset":10,"saatot":11,"saatto_yritykset":18,"etenemiset":9,"eteneminen_yritykset":14,"haavat":4,"palot":1,"stadium":"Kankaanpää Areena","tehot":2,"kl_pct":0.5},{"player_id":12903,"season_id":3,"match_id":129600,"date":"2026-05-31","team":"KaMa","opponent":"Jkl Kiri","home":0,"turns_at_bat":6,"kunnarit":0,"lyodyt":1,"tuodut":0,"karkilyonnit":3,"karki_yritykset":4,"saatot":8,"saatto_yritykset":11,"etenemiset":6,"eteneminen_yritykset":12,"haavat":1,"palot":5,"stadium":"Hippoksen pesäpallostadion, Jyväskylä","tehot":1,"kl_pct":0.75},{"player_id":12903,"season_id":3,"match_id":129667,"date":"2026-06-02","team":"KaMa","opponent":"SiiPe","home":1,"turns_at_bat":7,"kunnarit":0,"lyodyt":0,"tuodut":0,"karkilyonnit":6,"karki_yritykset":8,"saatot":12,"saatto_yritykset":17,"etenemiset":7,"eteneminen_yritykset":12,"haavat":4,"palot":1,"stadium":"Kankaanpää Areena","tehot":0,"kl_pct":0.75},{"player_id":12903,"season_id":3,"match_id":129606,"date":"2026-06-05","team":"KaMa","opponent":"SiKi","home":1,"turns_at_bat":5,"kunnarit":0,"lyodyt":0,"tuodut":0,"karkilyonnit":1,"karki_yritykset":4,"saatot":9,"saatto_yritykset":12,"etenemiset":8,"eteneminen_yritykset":9,"haavat":0,"palot":1,"stadium":"Kankaanpää Areena","tehot":0,"kl_pct":0.25},{"player_id":12903,"season_id":3,"match_id":129616,"date":"2026-06-11","team":"KaMa","opponent":"Ura","home":0,"turns_at_bat":6,"kunnarit":0,"lyodyt":0,"tuodut":0,"karkilyonnit":3,"karki_yritykset":4,"saatot":7,"saatto_yritykset":12,"etenemiset":4,"eteneminen_yritykset":8,"haavat":2,"palot":2,"stadium":"Neoen Areena, Kannus","tehot":0,"kl_pct":0.75},{"player_id":12903,"season_id":3,"match_id":129614,"date":"2026-06-12","team":"KaMa","opponent":"SiKi","home":0,"turns_at_bat":3,"kunnarit":0,"lyodyt":0,"tuodut":0,"karkilyonnit":1,"karki_yritykset":1,"saatot":1,"saatto_yritykset":2,"etenemiset":3,"eteneminen_yritykset":6,"haavat":1,"palot":2,"stadium":"Tuulivoima-areena, Simo","tehot":0,"kl_pct":1.0},{"player_id":12903,"season_id":3,"match_id":129625,"date":"2026-06-23","team":"KaMa","opponent":"HP","home":1,"turns_at_bat":4,"kunnarit":0,"lyodyt":0,"tuodut":0,"karkilyonnit":2,"karki_yritykset":2,"saatot":5,"saatto_yritykset":6,"etenemiset":3,"eteneminen_yritykset":6,"haavat":2,"palot":1,"stadium":"Kankaanpää Areena","tehot":0,"kl_pct":1.0},{"player_id":12903,"season_id":3,"match_id":129630,"date":"2026-06-26","team":"KaMa","opponent":"PuPe","home":0,"turns_at_bat":4,"kunnarit":0,"lyodyt":0,"tuodut":0,"karkilyonnit":1,"karki_yritykset":5,"saatot":4,"saatto_yritykset":8,"etenemiset":3,"eteneminen_yritykset":5,"haavat":0,"palot":2,"stadium":"Osuma Areena, Kuopio","tehot":0,"kl_pct":0.2},{"player_id":12903,"season_id":3,"match_id":129634,"date":"2026-06-27","team":"KaMa","opponent":"SiiPe","home":0,"turns_at_bat":2,"kunnarit":0,"lyodyt":0,"tuodut":0,"karkilyonnit":1,"karki_yritykset":2,"saatot":2,"saatto_yritykset":3,"etenemiset":1,"eteneminen_yritykset":2,"haavat":0,"palot":1,"stadium":"Mantun kenttä, Siilinjärvi","tehot":0,"kl_pct":0.5},{"player_id":12903,"season_id":3,"match_id":129638,"date":"2026-07-01","team":"KaMa","opponent":"PuMu","home":0,"turns_at_bat":5,"kunnarit":0,"lyodyt":1,"tuodut":0,"karkilyonnit":4,"karki_yritykset":7,"saatot":9,"saatto_yritykset":14,"etenemiset":6,"eteneminen_yritykset":10,"haavat":3,"palot":1,"stadium":"Good Guy Stadion, Meilahti (Helsinki)","tehot":1,"kl_pct":0.5714285714285714}],"comps":[]}