{"player":{"id":1465,"name":"Emmi Kaupinharju","born_year":null},"career":[{"year":2002,"season_id":32,"team":"Fera","age":null,"games":2,"turns_at_bat":12,"vyk":-0.07,"spark_index":69,"adv_plus":64,"runner_plus":53,"out_avoid_plus":107,"money_kl_plus":null,"teho_plus":0,"teho_plus_adj":0},{"year":2003,"season_id":36,"team":"Fera","age":null,"games":20,"turns_at_bat":105,"vyk":-0.05,"spark_index":82,"adv_plus":69,"runner_plus":74,"out_avoid_plus":124,"money_kl_plus":33,"teho_plus":25,"teho_plus_adj":25},{"year":2004,"season_id":40,"team":"Fera","age":null,"games":15,"turns_at_bat":89,"vyk":-0.21,"spark_index":79,"adv_plus":72,"runner_plus":69,"out_avoid_plus":112,"money_kl_plus":0,"teho_plus":11,"teho_plus_adj":11},{"year":2005,"season_id":44,"team":"Fera","age":null,"games":20,"turns_at_bat":111,"vyk":-0.62,"spark_index":87,"adv_plus":81,"runner_plus":83,"out_avoid_plus":108,"money_kl_plus":22,"teho_plus":19,"teho_plus_adj":19},{"year":2006,"season_id":48,"team":"Pesäkarhut","age":null,"games":20,"turns_at_bat":126,"vyk":-0.74,"spark_index":85,"adv_plus":74,"runner_plus":81,"out_avoid_plus":119,"money_kl_plus":45,"teho_plus":31,"teho_plus_adj":31},{"year":2007,"season_id":52,"team":"Fera","age":null,"games":19,"turns_at_bat":107,"vyk":-0.28,"spark_index":76,"adv_plus":64,"runner_plus":74,"out_avoid_plus":109,"money_kl_plus":67,"teho_plus":28,"teho_plus_adj":28}],"line":{"player_id":1465,"name":"Emmi Kaupinharju","born_year":null,"year":2007,"games":19,"team":"Fera","turns_at_bat":107,"kunnarit":0,"lyodyt":3,"tuodut":3,"karkilyonnit":30,"karki_yritykset":96,"saatot":58,"saatto_yritykset":145,"etenemiset":71,"eteneminen_yritykset":160,"haavat":63,"palot":26,"season_id":52,"tehot":6,"kl_pct":0.3125,"saatto_pct":0.4,"eten_pct":0.44375,"kunnari_rate":0.0,"lyoty_rate":0.028037383177570093,"tuotu_rate":0.01875,"haava_rate":0.5887850467289719,"palo_rate":0.24299065420560748,"tehot_per_turn":0.056074766355140186,"kl_per_turn":0.2803738317757009,"hr_rbi_per_turn":0.028037383177570093,"kl_base0":0.33962264150943394,"kl_base0_tries":53,"kl_base1":0.25,"kl_base1_tries":24,"kl_base2":0.3,"kl_base2_tries":10,"kl_base3":0.3333333333333333,"kl_base3_tries":9,"adv1_pct":0.33962264150943394,"adv2_pct":0.25,"adv3_pct":0.3,"adv_home_pct":0.3333333333333333,"money_kl_pct":0.3333333333333333,"money_kl_tries":9,"pos":"L","teho_plus":28,"adv_plus":64,"runner_plus":74,"out_avoid_plus":109,"adv1_plus":72,"adv2_plus":48,"adv3_plus":47,"adv_home_plus":67,"money_kl_plus":67,"spark_index":76,"run_value":5.785299090730408,"raa":-10.7,"jyk":-4.4,"vyk":-0.28,"teho_plus_adj":28,"pct_kl_pct":1,"pct_saatto_pct":4,"pct_eten_pct":4,"pct_kunnari_rate":26,"pct_lyoty_rate":33,"pct_palo_rate":69,"pct_tehot_per_turn":7},"proj":null,"translation":null,"pitching":null,"career_json":[{"year":2002,"kl_pct":0.42857142857142855,"teho_plus":0},{"year":2003,"kl_pct":0.37362637362637363,"teho_plus":25},{"year":2004,"kl_pct":0.4393939393939394,"teho_plus":11},{"year":2005,"kl_pct":0.4444444444444444,"teho_plus":19},{"year":2006,"kl_pct":0.40425531914893614,"teho_plus":31},{"year":2007,"kl_pct":0.3125,"teho_plus":28}],"pct_stats":["kl_pct","saatto_pct","eten_pct","kunnari_rate","lyoty_rate","palo_rate","tehot_per_turn"],"base_kl":{"player_id":1465,"turns_at_bat":107,"kl_base0":0.33962264150943394,"kl_base0_tries":53,"kl_base1":0.25,"kl_base1_tries":24,"kl_base2":0.3,"kl_base2_tries":10,"kl_base3":0.3333333333333333,"kl_base3_tries":9,"pct_kl_base0":21,"pct_kl_base1":8,"pct_kl_base2":0,"pct_kl_base3":20},"base_keys":["kl_base0","kl_base1","kl_base2","kl_base3"],"comps":[]}