{"player":{"id":1550,"name":"Eetu Ikonen","born_year":null},"career":[{"year":2015,"age":null,"games":23,"turns_at_bat":162,"vyk":0.3,"spark_index":104,"adv_plus":110,"runner_plus":98,"out_avoid_plus":97,"money_kl_plus":90,"teho_plus":58,"teho_plus_adj":58},{"year":2017,"age":null,"games":4,"turns_at_bat":24,"vyk":0.06,"spark_index":95,"adv_plus":86,"runner_plus":88,"out_avoid_plus":128,"money_kl_plus":205,"teho_plus":44,"teho_plus_adj":43}],"line":{"player_id":1550,"name":"Eetu Ikonen","born_year":null,"year":2017,"games":4,"team":"LievKi","turns_at_bat":24,"kunnarit":0,"lyodyt":1,"tuodut":1,"karkilyonnit":9,"karki_yritykset":22,"saatot":20,"saatto_yritykset":37,"etenemiset":22,"eteneminen_yritykset":42,"haavat":18,"palot":2,"season_id":101,"tehot":2,"kl_pct":0.4090909090909091,"saatto_pct":0.5405405405405406,"eten_pct":0.5238095238095238,"kunnari_rate":0.0,"lyoty_rate":0.041666666666666664,"tuotu_rate":0.023809523809523808,"haava_rate":0.75,"palo_rate":0.08333333333333333,"tehot_per_turn":0.08333333333333333,"kl_per_turn":0.375,"hr_rbi_per_turn":0.041666666666666664,"kl_base0":0.375,"kl_base0_tries":8,"kl_base1":0.3333333333333333,"kl_base1_tries":9,"kl_base2":0.5,"kl_base2_tries":4,"kl_base3":1.0,"kl_base3_tries":1,"adv1_pct":0.375,"adv2_pct":0.3333333333333333,"adv3_pct":0.5,"adv_home_pct":1.0,"money_kl_pct":1.0,"money_kl_tries":1,"pos":"L","teho_plus":44,"adv_plus":86,"runner_plus":88,"out_avoid_plus":128,"adv1_plus":74,"adv2_plus":67,"adv3_plus":81,"adv_home_plus":205,"money_kl_plus":205,"spark_index":95,"run_value":1.0827689811091268,"raa":-0.2,"jyk":1.0,"vyk":0.06,"teho_plus_adj":43,"pct_kl_pct":null,"pct_saatto_pct":null,"pct_eten_pct":null,"pct_kunnari_rate":null,"pct_lyoty_rate":null,"pct_palo_rate":null,"pct_tehot_per_turn":null},"proj":null,"translation":null,"pitching":null,"career_json":[{"year":2015,"kl_pct":0.5694444444444444,"teho_plus":58},{"year":2017,"kl_pct":0.4090909090909091,"teho_plus":44}],"pct_stats":["kl_pct","saatto_pct","eten_pct","kunnari_rate","lyoty_rate","palo_rate","tehot_per_turn"],"base_kl":{"player_id":1550,"turns_at_bat":24,"kl_base0":0.375,"kl_base0_tries":8,"kl_base1":0.3333333333333333,"kl_base1_tries":9,"kl_base2":0.5,"kl_base2_tries":4,"kl_base3":1.0,"kl_base3_tries":1,"pct_kl_base0":null,"pct_kl_base1":null,"pct_kl_base2":null,"pct_kl_base3":null},"base_keys":["kl_base0","kl_base1","kl_base2","kl_base3"],"comps":[]}