{"player":{"id":1625,"name":"Antti Remes","born_year":null},"career":[{"year":2000,"age":null,"games":3,"turns_at_bat":8,"vyk":-0.04,"spark_index":45,"adv_plus":18,"runner_plus":38,"out_avoid_plus":123,"money_kl_plus":0,"teho_plus":0,"teho_plus_adj":0},{"year":2001,"age":null,"games":1,"turns_at_bat":2,"vyk":-0.01,"spark_index":29,"adv_plus":0,"runner_plus":0,"out_avoid_plus":143,"money_kl_plus":null,"teho_plus":0,"teho_plus_adj":0}],"line":{"player_id":1625,"name":"Antti Remes","born_year":null,"year":2001,"games":1,"team":"JoMa","turns_at_bat":2,"kunnarit":0,"lyodyt":0,"tuodut":0,"karkilyonnit":0,"karki_yritykset":3,"saatot":0,"saatto_yritykset":5,"etenemiset":0,"eteneminen_yritykset":2,"haavat":2,"palot":0,"season_id":38,"tehot":0,"kl_pct":0.0,"saatto_pct":0.0,"eten_pct":0.0,"kunnari_rate":0.0,"lyoty_rate":0.0,"tuotu_rate":0.0,"haava_rate":1.0,"palo_rate":0.0,"tehot_per_turn":0.0,"kl_per_turn":0.0,"hr_rbi_per_turn":0.0,"kl_base0":null,"kl_base0_tries":0,"kl_base1":0.0,"kl_base1_tries":2,"kl_base2":0.0,"kl_base2_tries":1,"kl_base3":null,"kl_base3_tries":0,"adv1_pct":null,"adv2_pct":0.0,"adv3_pct":0.0,"adv_home_pct":null,"money_kl_pct":null,"money_kl_tries":0,"pos":null,"teho_plus":0,"adv_plus":0,"runner_plus":0,"out_avoid_plus":143,"adv1_plus":null,"adv2_plus":0,"adv3_plus":0,"adv_home_plus":null,"money_kl_plus":null,"spark_index":29,"run_value":-0.06592468095759767,"raa":-0.3,"jyk":-0.2,"vyk":-0.01,"teho_plus_adj":0,"pct_kl_pct":null,"pct_saatto_pct":null,"pct_eten_pct":null,"pct_kunnari_rate":null,"pct_lyoty_rate":null,"pct_palo_rate":null,"pct_tehot_per_turn":null},"proj":null,"career_json":[{"year":2000,"kl_pct":0.0,"teho_plus":0},{"year":2001,"kl_pct":0.0,"teho_plus":0}],"pct_stats":["kl_pct","saatto_pct","eten_pct","kunnari_rate","lyoty_rate","palo_rate","tehot_per_turn"],"base_kl":{"player_id":1625,"turns_at_bat":2,"kl_base0":null,"kl_base0_tries":0,"kl_base1":0.0,"kl_base1_tries":2,"kl_base2":0.0,"kl_base2_tries":1,"kl_base3":null,"kl_base3_tries":0,"pct_kl_base0":null,"pct_kl_base1":null,"pct_kl_base2":null,"pct_kl_base3":null},"base_keys":["kl_base0","kl_base1","kl_base2","kl_base3"],"comps":[]}