{"player":{"id":17754,"name":"Mirella Nygård","born_year":null},"career":[{"year":2023,"season_id":175,"team":"AA","age":null,"games":2,"turns_at_bat":11,"vyk":-0.04,"spark_index":62,"adv_plus":44,"runner_plus":54,"out_avoid_plus":118,"money_kl_plus":43,"teho_plus":30,"teho_plus_adj":30},{"year":2024,"season_id":176,"team":"AA","age":null,"games":8,"turns_at_bat":60,"vyk":0.04,"spark_index":87,"adv_plus":80,"runner_plus":82,"out_avoid_plus":114,"money_kl_plus":96,"teho_plus":98,"teho_plus_adj":101},{"year":2025,"season_id":126,"team":"AA","age":null,"games":22,"turns_at_bat":131,"vyk":0.87,"spark_index":99,"adv_plus":92,"runner_plus":97,"out_avoid_plus":120,"money_kl_plus":124,"teho_plus":159,"teho_plus_adj":156},{"year":2025,"season_id":177,"team":"AA","age":null,"games":3,"turns_at_bat":20,"vyk":0.11,"spark_index":110,"adv_plus":103,"runner_plus":112,"out_avoid_plus":124,"money_kl_plus":109,"teho_plus":150,"teho_plus_adj":150},{"year":2026,"season_id":130,"team":"AA","age":null,"games":17,"turns_at_bat":91,"vyk":0.53,"spark_index":108,"adv_plus":111,"runner_plus":104,"out_avoid_plus":105,"money_kl_plus":107,"teho_plus":122,"teho_plus_adj":119},{"year":2026,"season_id":178,"team":"AA","age":null,"games":1,"turns_at_bat":7,"vyk":0.01,"spark_index":103,"adv_plus":95,"runner_plus":89,"out_avoid_plus":145,"money_kl_plus":87,"teho_plus":47,"teho_plus_adj":47}],"line":{"player_id":17754,"name":"Mirella Nygård","born_year":null,"year":2026,"games":1,"team":"AA","turns_at_bat":7,"kunnarit":0,"lyodyt":1,"tuodut":0,"karkilyonnit":2,"karki_yritykset":4,"saatot":9,"saatto_yritykset":14,"etenemiset":7,"eteneminen_yritykset":12,"haavat":5,"palot":0,"season_id":178,"tehot":1,"kl_pct":0.5,"saatto_pct":0.6428571428571429,"eten_pct":0.5833333333333334,"kunnari_rate":0.0,"lyoty_rate":0.14285714285714285,"tuotu_rate":0.0,"haava_rate":0.7142857142857143,"palo_rate":0.0,"tehot_per_turn":0.14285714285714285,"kl_per_turn":0.2857142857142857,"hr_rbi_per_turn":0.14285714285714285,"kl_base0":null,"kl_base0_tries":0,"kl_base1":0.5,"kl_base1_tries":2,"kl_base2":null,"kl_base2_tries":0,"kl_base3":0.5,"kl_base3_tries":2,"adv1_pct":null,"adv2_pct":0.5,"adv3_pct":null,"adv_home_pct":0.5,"money_kl_pct":0.5,"money_kl_tries":2,"pos":"2K","teho_plus":47,"adv_plus":95,"runner_plus":89,"out_avoid_plus":145,"adv1_plus":null,"adv2_plus":84,"adv3_plus":null,"adv_home_plus":87,"money_kl_plus":87,"spark_index":103,"run_value":0.6637177699468543,"raa":-0.4,"jyk":0.2,"vyk":0.01,"teho_plus_adj":47,"pct_kl_pct":null,"pct_saatto_pct":null,"pct_eten_pct":null,"pct_kunnari_rate":null,"pct_lyoty_rate":null,"pct_palo_rate":null,"pct_tehot_per_turn":null},"proj":{"player_id":17754,"name":"Mirella Nygård","as_of":"2026-07-13","age":null,"stats":{"kl_pct":{"rate":0.5807742723861019,"effective_n":136.7461001529116,"observed":0.5702417167997257},"saatto_pct":{"rate":0.669174263786924,"effective_n":283.08360513661677,"observed":0.6704209330315752},"eten_pct":{"rate":0.6460794325458364,"effective_n":239.67474776567462,"observed":0.6434670777982232},"kunnari_rate":{"rate":0.007551625596261087,"effective_n":177.22964270772286,"observed":0.0055831476577298715},"lyoty_rate":{"rate":0.18972509821538086,"effective_n":144.0975602843885,"observed":0.22185793599291284},"haava_rate":{"rate":0.4030341782249624,"effective_n":107.92014770734937,"observed":0.43397651490974715},"palo_rate":{"rate":0.2761501259655683,"effective_n":122.52931041834152,"observed":0.2551520978555326}},"teho_plus_proj":130},"translation":null,"pitching":null,"career_json":[{"year":2023,"kl_pct":0.2222222222222222,"teho_plus":30},{"year":2024,"kl_pct":0.5094339622641509,"teho_plus":98},{"year":2025,"kl_pct":0.5271317829457365,"teho_plus":159},{"year":2025,"kl_pct":0.6666666666666666,"teho_plus":150},{"year":2026,"kl_pct":0.6,"teho_plus":122},{"year":2026,"kl_pct":0.5,"teho_plus":47}],"pct_stats":["kl_pct","saatto_pct","eten_pct","kunnari_rate","lyoty_rate","palo_rate","tehot_per_turn"],"base_kl":{"player_id":17754,"turns_at_bat":7,"kl_base0":null,"kl_base0_tries":0,"kl_base1":0.5,"kl_base1_tries":2,"kl_base2":null,"kl_base2_tries":0,"kl_base3":0.5,"kl_base3_tries":2,"pct_kl_base0":null,"pct_kl_base1":null,"pct_kl_base2":null,"pct_kl_base3":null},"base_keys":["kl_base0","kl_base1","kl_base2","kl_base3"],"comps":[]}