{"player":{"id":2746,"name":"Marko Toijonen","born_year":null},"career":[{"year":2002,"season_id":33,"team":"Mäntyharju","age":null,"games":19,"turns_at_bat":108,"vyk":0.22,"spark_index":92,"adv_plus":88,"runner_plus":85,"out_avoid_plus":115,"money_kl_plus":123,"teho_plus":90,"teho_plus_adj":89}],"line":{"player_id":2746,"name":"Marko Toijonen","born_year":null,"year":2002,"games":19,"team":"Mäntyharju","turns_at_bat":108,"kunnarit":2,"lyodyt":13,"tuodut":3,"karkilyonnit":46,"karki_yritykset":102,"saatot":110,"saatto_yritykset":207,"etenemiset":88,"eteneminen_yritykset":174,"haavat":66,"palot":20,"season_id":33,"tehot":18,"kl_pct":0.45098039215686275,"saatto_pct":0.5314009661835749,"eten_pct":0.5057471264367817,"kunnari_rate":0.018518518518518517,"lyoty_rate":0.12037037037037036,"tuotu_rate":0.017241379310344827,"haava_rate":0.6111111111111112,"palo_rate":0.18518518518518517,"tehot_per_turn":0.16666666666666666,"kl_per_turn":0.42592592592592593,"hr_rbi_per_turn":0.1388888888888889,"kl_base0":0.3448275862068966,"kl_base0_tries":29,"kl_base1":0.34782608695652173,"kl_base1_tries":23,"kl_base2":0.5416666666666666,"kl_base2_tries":24,"kl_base3":0.5769230769230769,"kl_base3_tries":26,"adv1_pct":0.3448275862068966,"adv2_pct":0.34782608695652173,"adv3_pct":0.5416666666666666,"adv_home_pct":0.5769230769230769,"money_kl_pct":0.5769230769230769,"money_kl_tries":26,"pos":"L","teho_plus":90,"adv_plus":88,"runner_plus":85,"out_avoid_plus":115,"adv1_plus":67,"adv2_plus":66,"adv3_plus":88,"adv_home_plus":123,"money_kl_plus":123,"spark_index":92,"run_value":10.867626482415002,"raa":-1.2,"jyk":3.3,"vyk":0.22,"teho_plus_adj":89,"pct_kl_pct":27,"pct_saatto_pct":31,"pct_eten_pct":19,"pct_kunnari_rate":90,"pct_lyoty_rate":80,"pct_palo_rate":83,"pct_tehot_per_turn":50},"proj":null,"translation":null,"pitching":null,"career_json":[{"year":2002,"kl_pct":0.45098039215686275,"teho_plus":90}],"pct_stats":["kl_pct","saatto_pct","eten_pct","kunnari_rate","lyoty_rate","palo_rate","tehot_per_turn"],"base_kl":{"player_id":2746,"turns_at_bat":108,"kl_base0":0.3448275862068966,"kl_base0_tries":29,"kl_base1":0.34782608695652173,"kl_base1_tries":23,"kl_base2":0.5416666666666666,"kl_base2_tries":24,"kl_base3":0.5769230769230769,"kl_base3_tries":26,"pct_kl_base0":17,"pct_kl_base1":26,"pct_kl_base2":39,"pct_kl_base3":76},"base_keys":["kl_base0","kl_base1","kl_base2","kl_base3"],"comps":[]}