{"player":{"id":2968,"name":"Laura Vauhkonen","born_year":null},"career":[{"year":2003,"season_id":38,"team":"SiiPe","age":null,"games":9,"turns_at_bat":42,"vyk":0.02,"spark_index":94,"adv_plus":86,"runner_plus":93,"out_avoid_plus":118,"money_kl_plus":67,"teho_plus":64,"teho_plus_adj":65},{"year":2005,"season_id":161,"team":"SiiPe","age":null,"games":7,"turns_at_bat":43,"vyk":0.05,"spark_index":103,"adv_plus":104,"runner_plus":96,"out_avoid_plus":110,"money_kl_plus":42,"teho_plus":51,"teho_plus_adj":51}],"line":{"player_id":2968,"name":"Laura Vauhkonen","born_year":null,"year":2005,"games":7,"team":"SiiPe","turns_at_bat":43,"kunnarit":0,"lyodyt":1,"tuodut":6,"karkilyonnit":18,"karki_yritykset":28,"saatot":38,"saatto_yritykset":54,"etenemiset":53,"eteneminen_yritykset":82,"haavat":18,"palot":11,"season_id":161,"tehot":7,"kl_pct":0.6428571428571429,"saatto_pct":0.7037037037037037,"eten_pct":0.6463414634146342,"kunnari_rate":0.0,"lyoty_rate":0.023255813953488372,"tuotu_rate":0.07317073170731707,"haava_rate":0.4186046511627907,"palo_rate":0.2558139534883721,"tehot_per_turn":0.16279069767441862,"kl_per_turn":0.4186046511627907,"hr_rbi_per_turn":0.023255813953488372,"kl_base0":0.6470588235294118,"kl_base0_tries":17,"kl_base1":1.0,"kl_base1_tries":4,"kl_base2":0.6666666666666666,"kl_base2_tries":3,"kl_base3":0.25,"kl_base3_tries":4,"adv1_pct":0.6470588235294118,"adv2_pct":1.0,"adv3_pct":0.6666666666666666,"adv_home_pct":0.25,"money_kl_pct":0.25,"money_kl_tries":4,"pos":"S","teho_plus":51,"adv_plus":104,"runner_plus":96,"out_avoid_plus":110,"adv1_plus":106,"adv2_plus":159,"adv3_plus":96,"adv_home_plus":42,"money_kl_plus":42,"spark_index":103,"run_value":3.5225668051495633,"raa":-3.4,"jyk":1.1,"vyk":0.05,"teho_plus_adj":51,"pct_kl_pct":56,"pct_saatto_pct":64,"pct_eten_pct":41,"pct_kunnari_rate":25,"pct_lyoty_rate":9,"pct_palo_rate":80,"pct_tehot_per_turn":17},"proj":null,"translation":null,"pitching":null,"career_json":[{"year":2003,"kl_pct":0.5,"teho_plus":64},{"year":2005,"kl_pct":0.6428571428571429,"teho_plus":51}],"pct_stats":["kl_pct","saatto_pct","eten_pct","kunnari_rate","lyoty_rate","palo_rate","tehot_per_turn"],"base_kl":{"player_id":2968,"turns_at_bat":43,"kl_base0":0.6470588235294118,"kl_base0_tries":17,"kl_base1":1.0,"kl_base1_tries":4,"kl_base2":0.6666666666666666,"kl_base2_tries":3,"kl_base3":0.25,"kl_base3_tries":4,"pct_kl_base0":60,"pct_kl_base1":99,"pct_kl_base2":47,"pct_kl_base3":7},"base_keys":["kl_base0","kl_base1","kl_base2","kl_base3"],"comps":[]}