{"player":{"id":6075,"name":"Tiina Kärki","born_year":null},"career":[{"year":2009,"age":null,"games":9,"turns_at_bat":62,"vyk":0.39,"spark_index":109,"adv_plus":108,"runner_plus":113,"out_avoid_plus":104,"money_kl_plus":108,"teho_plus":143,"teho_plus_adj":134},{"year":2010,"age":null,"games":14,"turns_at_bat":116,"vyk":0.29,"spark_index":99,"adv_plus":97,"runner_plus":103,"out_avoid_plus":96,"money_kl_plus":86,"teho_plus":98,"teho_plus_adj":92},{"year":2011,"age":null,"games":14,"turns_at_bat":120,"vyk":0.29,"spark_index":100,"adv_plus":98,"runner_plus":108,"out_avoid_plus":94,"money_kl_plus":87,"teho_plus":102,"teho_plus_adj":94},{"year":2012,"age":null,"games":21,"turns_at_bat":145,"vyk":-0.22,"spark_index":90,"adv_plus":90,"runner_plus":90,"out_avoid_plus":88,"money_kl_plus":163,"teho_plus":69,"teho_plus_adj":69}],"line":{"player_id":6075,"name":"Tiina Kärki","born_year":null,"year":2012,"games":21,"team":"KeKi","turns_at_bat":145,"kunnarit":1,"lyodyt":2,"tuodut":15,"karkilyonnit":56,"karki_yritykset":133,"saatot":112,"saatto_yritykset":201,"etenemiset":135,"eteneminen_yritykset":256,"haavat":66,"palot":55,"season_id":80,"tehot":18,"kl_pct":0.42105263157894735,"saatto_pct":0.5572139303482587,"eten_pct":0.52734375,"kunnari_rate":0.006896551724137931,"lyoty_rate":0.013793103448275862,"tuotu_rate":0.05859375,"haava_rate":0.45517241379310347,"palo_rate":0.3793103448275862,"tehot_per_turn":0.12413793103448276,"kl_per_turn":0.38620689655172413,"hr_rbi_per_turn":0.020689655172413793,"kl_base0":0.3333333333333333,"kl_base0_tries":69,"kl_base1":0.4807692307692308,"kl_base1_tries":52,"kl_base2":0.625,"kl_base2_tries":8,"kl_base3":0.75,"kl_base3_tries":4,"adv1_pct":0.3333333333333333,"adv2_pct":0.4807692307692308,"adv3_pct":0.625,"adv_home_pct":0.75,"money_kl_pct":0.75,"money_kl_tries":4,"pos":"2V","teho_plus":69,"adv_plus":90,"runner_plus":90,"out_avoid_plus":88,"adv1_plus":74,"adv2_plus":96,"adv3_plus":98,"adv_home_plus":163,"money_kl_plus":163,"spark_index":90,"run_value":-3.2407342177824496,"raa":-8.7,"jyk":-3.2,"vyk":-0.22,"teho_plus_adj":69,"pct_kl_pct":34,"pct_saatto_pct":52,"pct_eten_pct":40,"pct_kunnari_rate":67,"pct_lyoty_rate":22,"pct_palo_rate":20,"pct_tehot_per_turn":47},"proj":null,"career_json":[{"year":2009,"kl_pct":0.6382978723404256,"teho_plus":143},{"year":2010,"kl_pct":0.6336633663366337,"teho_plus":98},{"year":2011,"kl_pct":0.6274509803921569,"teho_plus":102},{"year":2012,"kl_pct":0.42105263157894735,"teho_plus":69}],"pct_stats":["kl_pct","saatto_pct","eten_pct","kunnari_rate","lyoty_rate","palo_rate","tehot_per_turn"],"base_kl":{"player_id":6075,"turns_at_bat":145,"kl_base0":0.3333333333333333,"kl_base0_tries":69,"kl_base1":0.4807692307692308,"kl_base1_tries":52,"kl_base2":0.625,"kl_base2_tries":8,"kl_base3":0.75,"kl_base3_tries":4,"pct_kl_base0":22,"pct_kl_base1":58,"pct_kl_base2":56,"pct_kl_base3":94},"base_keys":["kl_base0","kl_base1","kl_base2","kl_base3"],"comps":[]}