{"player":{"id":6133,"name":"Veera Korhonen","born_year":null},"career":[{"year":2012,"season_id":164,"team":"KaKa","age":null,"games":7,"turns_at_bat":17,"vyk":0.07,"spark_index":105,"adv_plus":99,"runner_plus":103,"out_avoid_plus":123,"money_kl_plus":108,"teho_plus":121,"teho_plus_adj":123}],"line":{"player_id":6133,"name":"Veera Korhonen","born_year":null,"year":2012,"games":7,"team":"KaKa","turns_at_bat":17,"kunnarit":0,"lyodyt":5,"tuodut":1,"karkilyonnit":12,"karki_yritykset":20,"saatot":25,"saatto_yritykset":38,"etenemiset":15,"eteneminen_yritykset":22,"haavat":4,"palot":3,"season_id":164,"tehot":6,"kl_pct":0.6,"saatto_pct":0.6578947368421053,"eten_pct":0.6818181818181818,"kunnari_rate":0.0,"lyoty_rate":0.29411764705882354,"tuotu_rate":0.045454545454545456,"haava_rate":0.23529411764705882,"palo_rate":0.17647058823529413,"tehot_per_turn":0.35294117647058826,"kl_per_turn":0.7058823529411765,"hr_rbi_per_turn":0.29411764705882354,"kl_base0":0.0,"kl_base0_tries":1,"kl_base1":0.8,"kl_base1_tries":5,"kl_base2":0.5,"kl_base2_tries":6,"kl_base3":0.625,"kl_base3_tries":8,"adv1_pct":0.0,"adv2_pct":0.8,"adv3_pct":0.5,"adv_home_pct":0.625,"money_kl_pct":0.625,"money_kl_tries":8,"pos":"3V","teho_plus":121,"adv_plus":99,"runner_plus":103,"out_avoid_plus":123,"adv1_plus":0,"adv2_plus":132,"adv3_plus":72,"adv_home_plus":108,"money_kl_plus":108,"spark_index":105,"run_value":1.355103572625723,"raa":2.1,"jyk":1.4,"vyk":0.07,"teho_plus_adj":123,"pct_kl_pct":null,"pct_saatto_pct":null,"pct_eten_pct":null,"pct_kunnari_rate":null,"pct_lyoty_rate":null,"pct_palo_rate":null,"pct_tehot_per_turn":null},"proj":null,"translation":null,"pitching":null,"career_json":[{"year":2012,"kl_pct":0.6,"teho_plus":121}],"pct_stats":["kl_pct","saatto_pct","eten_pct","kunnari_rate","lyoty_rate","palo_rate","tehot_per_turn"],"base_kl":{"player_id":6133,"turns_at_bat":17,"kl_base0":0.0,"kl_base0_tries":1,"kl_base1":0.8,"kl_base1_tries":5,"kl_base2":0.5,"kl_base2_tries":6,"kl_base3":0.625,"kl_base3_tries":8,"pct_kl_base0":null,"pct_kl_base1":null,"pct_kl_base2":null,"pct_kl_base3":null},"base_keys":["kl_base0","kl_base1","kl_base2","kl_base3"],"comps":[]}