{"player":{"id":6358,"name":"Mikko Kylmäkorpi","born_year":null},"career":[{"year":2009,"season_id":139,"team":"Manse PP","age":null,"games":12,"turns_at_bat":61,"vyk":-0.35,"spark_index":59,"adv_plus":63,"runner_plus":56,"out_avoid_plus":52,"money_kl_plus":0,"teho_plus":0,"teho_plus_adj":0}],"line":{"player_id":6358,"name":"Mikko Kylmäkorpi","born_year":null,"year":2009,"games":12,"team":"Manse PP","turns_at_bat":61,"kunnarit":0,"lyodyt":0,"tuodut":0,"karkilyonnit":19,"karki_yritykset":51,"saatot":30,"saatto_yritykset":77,"etenemiset":28,"eteneminen_yritykset":79,"haavat":12,"palot":39,"season_id":139,"tehot":0,"kl_pct":0.37254901960784315,"saatto_pct":0.38961038961038963,"eten_pct":0.35443037974683544,"kunnari_rate":0.0,"lyoty_rate":0.0,"tuotu_rate":0.0,"haava_rate":0.19672131147540983,"palo_rate":0.639344262295082,"tehot_per_turn":0.0,"kl_per_turn":0.3114754098360656,"hr_rbi_per_turn":0.0,"kl_base0":0.4166666666666667,"kl_base0_tries":24,"kl_base1":0.4,"kl_base1_tries":15,"kl_base2":0.5,"kl_base2_tries":6,"kl_base3":0.0,"kl_base3_tries":6,"adv1_pct":0.4166666666666667,"adv2_pct":0.4,"adv3_pct":0.5,"adv_home_pct":0.0,"money_kl_pct":0.0,"money_kl_tries":6,"pos":"S","teho_plus":0,"adv_plus":63,"runner_plus":56,"out_avoid_plus":52,"adv1_plus":75,"adv2_plus":75,"adv3_plus":80,"adv_home_plus":0,"money_kl_plus":0,"spark_index":59,"run_value":-2.249888327804193,"raa":-10.8,"jyk":-6.3,"vyk":-0.35,"teho_plus_adj":0,"pct_kl_pct":7,"pct_saatto_pct":2,"pct_eten_pct":1,"pct_kunnari_rate":27,"pct_lyoty_rate":3,"pct_palo_rate":0,"pct_tehot_per_turn":0},"proj":null,"translation":null,"pitching":null,"career_json":[{"year":2009,"kl_pct":0.37254901960784315,"teho_plus":0}],"pct_stats":["kl_pct","saatto_pct","eten_pct","kunnari_rate","lyoty_rate","palo_rate","tehot_per_turn"],"base_kl":{"player_id":6358,"turns_at_bat":61,"kl_base0":0.4166666666666667,"kl_base0_tries":24,"kl_base1":0.4,"kl_base1_tries":15,"kl_base2":0.5,"kl_base2_tries":6,"kl_base3":0.0,"kl_base3_tries":6,"pct_kl_base0":22,"pct_kl_base1":28,"pct_kl_base2":27,"pct_kl_base3":3},"base_keys":["kl_base0","kl_base1","kl_base2","kl_base3"],"comps":[]}