{"player":{"id":8463,"name":"Janne Palomäki","born_year":null},"career":[{"year":2017,"season_id":93,"team":"Kiri","age":null,"games":18,"turns_at_bat":110,"vyk":-0.0,"spark_index":87,"adv_plus":83,"runner_plus":75,"out_avoid_plus":116,"money_kl_plus":154,"teho_plus":48,"teho_plus_adj":50},{"year":2021,"season_id":109,"team":"Lohi","age":null,"games":22,"turns_at_bat":160,"vyk":-0.1,"spark_index":102,"adv_plus":108,"runner_plus":99,"out_avoid_plus":93,"money_kl_plus":131,"teho_plus":96,"teho_plus_adj":103},{"year":2022,"season_id":113,"team":"Lohi","age":null,"games":13,"turns_at_bat":81,"vyk":-0.1,"spark_index":96,"adv_plus":99,"runner_plus":100,"out_avoid_plus":80,"money_kl_plus":0,"teho_plus":66,"teho_plus_adj":67},{"year":2023,"season_id":117,"team":"Lohi","age":null,"games":24,"turns_at_bat":166,"vyk":-0.71,"spark_index":102,"adv_plus":108,"runner_plus":100,"out_avoid_plus":92,"money_kl_plus":106,"teho_plus":82,"teho_plus_adj":89},{"year":2024,"season_id":121,"team":"Lohi","age":null,"games":22,"turns_at_bat":156,"vyk":0.76,"spark_index":102,"adv_plus":112,"runner_plus":102,"out_avoid_plus":75,"money_kl_plus":86,"teho_plus":64,"teho_plus_adj":71}],"line":{"player_id":8463,"name":"Janne Palomäki","born_year":null,"year":2024,"games":22,"team":"Lohi","turns_at_bat":156,"kunnarit":0,"lyodyt":2,"tuodut":16,"karkilyonnit":82,"karki_yritykset":139,"saatot":192,"saatto_yritykset":278,"etenemiset":196,"eteneminen_yritykset":317,"haavat":43,"palot":78,"season_id":121,"tehot":18,"kl_pct":0.5899280575539568,"saatto_pct":0.6906474820143885,"eten_pct":0.6182965299684543,"kunnari_rate":0.0,"lyoty_rate":0.01282051282051282,"tuotu_rate":0.050473186119873815,"haava_rate":0.27564102564102566,"palo_rate":0.5,"tehot_per_turn":0.11538461538461539,"kl_per_turn":0.5256410256410257,"hr_rbi_per_turn":0.01282051282051282,"kl_base0":0.5625,"kl_base0_tries":32,"kl_base1":0.5641025641025641,"kl_base1_tries":78,"kl_base2":0.75,"kl_base2_tries":24,"kl_base3":0.4,"kl_base3_tries":5,"adv1_pct":0.5625,"adv2_pct":0.5641025641025641,"adv3_pct":0.75,"adv_home_pct":0.4,"money_kl_pct":0.4,"money_kl_tries":5,"pos":"S","teho_plus":64,"adv_plus":112,"runner_plus":102,"out_avoid_plus":75,"adv1_plus":104,"adv2_plus":101,"adv3_plus":125,"adv_home_plus":86,"money_kl_plus":86,"spark_index":102,"run_value":29.25116041974574,"raa":1.5,"jyk":9.5,"vyk":0.76,"teho_plus_adj":71,"pct_kl_pct":72,"pct_saatto_pct":90,"pct_eten_pct":64,"pct_kunnari_rate":24,"pct_lyoty_rate":23,"pct_palo_rate":6,"pct_tehot_per_turn":26},"proj":null,"translation":null,"pitching":null,"career_json":[{"year":2017,"kl_pct":0.46236559139784944,"teho_plus":48},{"year":2021,"kl_pct":0.5655172413793104,"teho_plus":96},{"year":2022,"kl_pct":0.5,"teho_plus":66},{"year":2023,"kl_pct":0.5664335664335665,"teho_plus":82},{"year":2024,"kl_pct":0.5899280575539568,"teho_plus":64}],"pct_stats":["kl_pct","saatto_pct","eten_pct","kunnari_rate","lyoty_rate","palo_rate","tehot_per_turn"],"base_kl":{"player_id":8463,"turns_at_bat":156,"kl_base0":0.5625,"kl_base0_tries":32,"kl_base1":0.5641025641025641,"kl_base1_tries":78,"kl_base2":0.75,"kl_base2_tries":24,"kl_base3":0.4,"kl_base3_tries":5,"pct_kl_base0":70,"pct_kl_base1":60,"pct_kl_base2":82,"pct_kl_base3":29},"base_keys":["kl_base0","kl_base1","kl_base2","kl_base3"],"comps":[]}