{"player":{"id":9318,"name":"Melissa Karimies","born_year":null},"career":[{"year":2017,"season_id":169,"team":"Tahko","age":null,"games":7,"turns_at_bat":38,"vyk":-0.1,"spark_index":93,"adv_plus":105,"runner_plus":99,"out_avoid_plus":54,"money_kl_plus":null,"teho_plus":60,"teho_plus_adj":63},{"year":2018,"season_id":170,"team":"KiPe06","age":null,"games":9,"turns_at_bat":28,"vyk":-0.04,"spark_index":91,"adv_plus":90,"runner_plus":100,"out_avoid_plus":78,"money_kl_plus":0,"teho_plus":74,"teho_plus_adj":73}],"line":{"player_id":9318,"name":"Melissa Karimies","born_year":null,"year":2018,"games":9,"team":"KiPe06","turns_at_bat":28,"kunnarit":0,"lyodyt":0,"tuodut":6,"karkilyonnit":10,"karki_yritykset":18,"saatot":17,"saatto_yritykset":29,"etenemiset":39,"eteneminen_yritykset":59,"haavat":7,"palot":13,"season_id":170,"tehot":6,"kl_pct":0.5555555555555556,"saatto_pct":0.5862068965517241,"eten_pct":0.6610169491525424,"kunnari_rate":0.0,"lyoty_rate":0.0,"tuotu_rate":0.1016949152542373,"haava_rate":0.25,"palo_rate":0.4642857142857143,"tehot_per_turn":0.21428571428571427,"kl_per_turn":0.35714285714285715,"hr_rbi_per_turn":0.0,"kl_base0":0.6923076923076923,"kl_base0_tries":13,"kl_base1":null,"kl_base1_tries":0,"kl_base2":0.5,"kl_base2_tries":2,"kl_base3":0.0,"kl_base3_tries":3,"adv1_pct":0.6923076923076923,"adv2_pct":null,"adv3_pct":0.5,"adv_home_pct":0.0,"money_kl_pct":0.0,"money_kl_tries":3,"pos":null,"teho_plus":74,"adv_plus":90,"runner_plus":100,"out_avoid_plus":78,"adv1_plus":121,"adv2_plus":null,"adv3_plus":72,"adv_home_plus":0,"money_kl_plus":0,"spark_index":91,"run_value":1.129921498976059,"raa":-3.2,"jyk":-0.9,"vyk":-0.04,"teho_plus_adj":73,"pct_kl_pct":null,"pct_saatto_pct":null,"pct_eten_pct":null,"pct_kunnari_rate":null,"pct_lyoty_rate":null,"pct_palo_rate":null,"pct_tehot_per_turn":null},"proj":null,"translation":null,"pitching":null,"career_json":[{"year":2017,"kl_pct":0.6666666666666666,"teho_plus":60},{"year":2018,"kl_pct":0.5555555555555556,"teho_plus":74}],"pct_stats":["kl_pct","saatto_pct","eten_pct","kunnari_rate","lyoty_rate","palo_rate","tehot_per_turn"],"base_kl":{"player_id":9318,"turns_at_bat":28,"kl_base0":0.6923076923076923,"kl_base0_tries":13,"kl_base1":null,"kl_base1_tries":0,"kl_base2":0.5,"kl_base2_tries":2,"kl_base3":0.0,"kl_base3_tries":3,"pct_kl_base0":null,"pct_kl_base1":null,"pct_kl_base2":null,"pct_kl_base3":null},"base_keys":["kl_base0","kl_base1","kl_base2","kl_base3"],"comps":[]}